bajra/__init__.py
bajra/bajra.py
bajra/base.py
bajra/engines/__init__.py
bajra/engines/base.py
bajra/engines/mysql.py
bajra/engines/postgres.py
bajra-0.0.1.dist-info/LICENSE
bajra-0.0.1.dist-info/METADATA
bajra-0.0.1.dist-info/WHEEL
bajra-0.0.1.dist-info/top_level.txt
bajra-0.0.1.dist-info/RECORD
