Metadata-Version: 2.1
Name: bajra
Version: 0.0.1
Summary: A efficient raw SQL ORM
Home-page: https://github.com/Spratiher9/Bajra
Author: Souvik Pratiher
Author-email: spratiher9@gmail.com
License: UNKNOWN
Download-URL: https://github.com/Spratiher9/Bajra/archive/refs/tags/v0.0.1.tar.gz
Keywords: sql,orm,raw-sql,python,postgres,mysql,database
Platform: UNKNOWN
Classifier: Programming Language :: Python :: 3
Classifier: License :: OSI Approved :: Apache Software License
Classifier: Operating System :: OS Independent
Requires-Python: >=3.6
License-File: LICENSE
Requires-Dist: PyMySQL (==0.9.2)
Requires-Dist: psycopg2-binary (==2.9.3)
